wirepas_provisioning-1.1.data/data/wirepas_provisioning-extras/package/LICENSE
wirepas_provisioning-1.1.data/data/wirepas_provisioning-extras/package/README.md
wirepas_provisioning-1.1.data/data/wirepas_provisioning-extras/package/requirements.txt
wirepas_provisioning-1.1.data/data/wirepas_provisioning-extras/package/setup.py
wirepas_provisioning_server/__about__.py
wirepas_provisioning_server/__init__.py
wirepas_provisioning_server/data.py
wirepas_provisioning_server/events.py
wirepas_provisioning_server/message.py
wirepas_provisioning_server/provisioning_server.py
wirepas_provisioning_server/session.py
wirepas_provisioning-1.1.dist-info/LICENSE
wirepas_provisioning-1.1.dist-info/METADATA
wirepas_provisioning-1.1.dist-info/WHEEL
wirepas_provisioning-1.1.dist-info/entry_points.txt
wirepas_provisioning-1.1.dist-info/top_level.txt
wirepas_provisioning-1.1.dist-info/RECORD
