Metadata-Version: 2.1
Name: wirepas-provisioning
Version: 1.1
Summary: Wirepas provisioning server reference implementation.
Home-page: https://github.com/wirepas/wm-provisioning
Author: Wirepas Ltd
Author-email: opensource@wirepas.com
License: Apache-2
Keywords: wirepas connectivity iot mesh
Platform: UNKNOWN
Classifier: Development Status :: 5 - Production/Stable
Classifier: Intended Audience :: Developers
Classifier: License :: OSI Approved :: Apache Software License
Classifier: Topic :: Software Development :: Libraries
Classifier: Programming Language :: Python :: 3
Requires-Python: >=3.7
Requires-Dist: PyYAML (==5.3)
Requires-Dist: cbor2 (==4.1.2)
Requires-Dist: pycryptodome (==3.9.4)
Requires-Dist: wirepas-mqtt-library (==1.0)
